<?xml version='1.0' encoding='utf-8'?>
<tv><channel id="400477">
    <display-name lang="United Kingdom of Great Britain and Northern Ireland">TNT Sports 1 HD</display-name>
    <icon src="" />
  </channel>
  <programme channel="400477" start="20260111000000 +0000" stop="20260111010000 +0000">
    <title lang="zh">Isuzu UTE A-League</title>
    <desc>Macarthur FC v Sydney FC.</desc>
    <date>2026-01-11</date>
  </programme>
  <programme channel="400477" start="20260111010000 +0000" stop="20260111020000 +0000">
    <title lang="zh">Isuzu UTE A-League</title>
    <desc>Perth Glory v Central Coast Mariners.</desc>
    <date>2026-01-11</date>
  </programme>
  <programme channel="400477" start="20260111020000 +0000" stop="20260111040000 +0000">
    <title lang="zh">Live: Isuzu UTE A-League</title>
    <desc>Wellington Phoenix v Adelaide United (Kick-off 2.00am). All the action from the match at Sky Stadium.</desc>
    <date>2026-01-11</date>
  </programme>
  <programme channel="400477" start="20260111040000 +0000" stop="20260111043000 +0000">
    <title lang="zh">UEFA Champions League - Stories of the Finals</title>
    <desc>Take a look back to the 2013 final as Arjen Robben scored a dramatic late winner for Bayern to defeat Jurgen Klopp's Dortmund side. Plus, relive AC Milan v Juventus from 2003.</desc>
    <date>2026-01-11</date>
  </programme>
  <programme channel="400477" start="20260111043000 +0000" stop="20260111050000 +0000">
    <title lang="zh">UEFA Champions League - Stories of the Finals</title>
    <desc>Relive the controversial 1996 Champions League final between reigning champions Ajax and Marcello Lippi's Juventus. Plus, look back at Real Madrid's final against Bayer Leverkusen.</desc>
    <date>2026-01-11</date>
  </programme>
  <programme channel="400477" start="20260111050000 +0000" stop="20260111053000 +0000">
    <title lang="zh">UEFA Champions League - Stories of the Finals</title>
    <desc>A look back at Barcelona's memorable victory against Manchester United in 2011. Plus, highlights of the 2004 final between FC Porto and Monaco.</desc>
    <date>2026-01-11</date>
  </programme>
  <programme channel="400477" start="20260111053000 +0000" stop="20260111060000 +0000">
    <title lang="zh">UEFA Champions League - Stories of the Finals</title>
    <desc>We take a look back at Ajax's UEFA Champions League final against AC Milan's famous team in 1995 and Bayern Munich's dramatic victory over Valencia in the 2001 final.</desc>
    <date>2026-01-11</date>
  </programme>
  <programme channel="400477" start="20260111060000 +0000" stop="20260111080000 +0000">
    <title lang="zh">Live: Isuzu UTE A-League</title>
    <desc>Melbourne City v Newcastle Jets (Kick-off 6.00am). Coverage of the match at AAMI Park.</desc>
    <date>2026-01-11</date>
  </programme>
  <programme channel="400477" start="20260111080000 +0000" stop="20260111083000 +0000">
    <title lang="zh">The Breakdown</title>
    <desc>Darren Fletcher is joined by Steven Gerrard, Ally McCoist, Steve McManaman and Joleon Lescott to discuss England and Scotland's chances at the 2026 FIFA World Cup.</desc>
    <date>2026-01-11</date>
  </programme>
  <programme channel="400477" start="20260111083000 +0000" stop="20260111084500 +0000">
    <title lang="zh">Training Day</title>
    <desc>Peter Crouch, Steve Sidwell and Wayne Bridge head to west London to find out more about how Grenfell Athletic FC have been helping the community and bringing people together.</desc>
    <date>2026-01-11</date>
  </programme>
  <programme channel="400477" start="20260111084500 +0000" stop="20260111091500 +0000">
    <title lang="zh">Live: Luge World Cup</title>
    <desc>Coverage of run two of the women's doubles event in the latest meeting of the season from Winterberg, Germany.</desc>
    <date>2026-01-11</date>
  </programme>
  <programme channel="400477" start="20260111091500 +0000" stop="20260111104500 +0000">
    <title lang="zh">Live: Men's Alpine Skiing World Cup</title>
    <desc>Coverage of run one of the slalom in the latest meeting of the season from Adelboden, Switzerland.</desc>
    <date>2026-01-11</date>
  </programme>
  <programme channel="400477" start="20260111104500 +0000" stop="20260111123000 +0000">
    <title lang="zh">Live: Women's Alpine Skiing World Cup</title>
    <desc>Coverage of the super-G in the latest meeting of the season from Zauchensee, Austria.</desc>
    <date>2026-01-11</date>
  </programme>
  <programme channel="400477" start="20260111123000 +0000" stop="20260111133000 +0000">
    <title lang="zh">Live: Men's Alpine Skiing World Cup</title>
    <desc>Coverage of run two of the slalom in the latest meeting of the season from Adelboden, Switzerland.</desc>
    <date>2026-01-11</date>
  </programme>
  <programme channel="400477" start="20260111133000 +0000" stop="20260111163000 +0000">
    <title lang="zh">Live Emirates FA Cup</title>
    <desc>Portsmouth v Arsenal (Kick-off 2.00pm). All the action from the third-round tie at Fratton Park. The last of Pompey's two cup triumphs came in 2008, but they have endured some difficult years since then. Their opponents today are record 14-time winners of the competition, who are challenging for glory on all fronts this term.</desc>
    <date>2026-01-11</date>
  </programme>
  <programme channel="400477" start="20260111163000 +0000" stop="20260111190000 +0000">
    <title lang="zh">Live Emirates FA Cup</title>
    <desc>Manchester United v Brighton \u0026 Hove Albion (Kick-off 4.30pm). All the action from the third-round tie at Old Trafford. The sides have already met here in the Premier League this term, with United claiming a 4-2 win to avenge losses home and away to the Seagulls in the previous campaign. The hosts last won this competition in 2024 when they beat local rivals Manchester City 2-1 in the final.</desc>
    <date>2026-01-11</date>
  </programme>
  <programme channel="400477" start="20260111190000 +0000" stop="20260111213000 +0000">
    <title lang="zh">Live: Spanish Super Cup</title>
    <desc>Coverage of the final (Kick-off 7.00pm), which takes place at King Abdullah Sports City Stadium in Jeddah, Saudi Arabia.</desc>
    <date>2026-01-11</date>
  </programme>
  <programme channel="400477" start="20260111213000 +0000" stop="20260111223000 +0000">
    <title lang="zh">Dakar Rally Saudi Arabia</title>
    <desc>Stage eight, from Wadi Ad-Dawasir.</desc>
    <date>2026-01-11</date>
  </programme>
  <programme channel="400477" start="20260111223000 +0000" stop="20260111230000 +0000">
    <title lang="zh">TNT Sports Reload</title>
    <desc>The best bits from TNT Sports over the last week.</desc>
    <date>2026-01-11</date>
  </programme>
  <programme channel="400477" start="20260111230000 +0000" stop="20260112000000 +0000">
    <title lang="zh">The Emirates FA Cup</title>
    <desc>Derby County v Leeds United.</desc>
    <date>2026-01-11</date>
  </programme>
  <programme channel="400477" start="20260112000000 +0000" stop="20260112010000 +0000">
    <title lang="zh">The Emirates FA Cup</title>
    <desc>Portsmouth v Arsenal.</desc>
    <date>2026-01-12</date>
  </programme>
  <programme channel="400477" start="20260112010000 +0000" stop="20260112020000 +0000">
    <title lang="zh">The Emirates FA Cup</title>
    <desc>Manchester United v Brighton \u0026 Hove Albion.</desc>
    <date>2026-01-12</date>
  </programme>
  <programme channel="400477" start="20260112020000 +0000" stop="20260112030000 +0000">
    <title lang="zh">Spanish Super Cup</title>
    <desc>Action from the final, which took place at King Abdullah Sports City Stadium in Jeddah, Saudi Arabia.</desc>
    <date>2026-01-12</date>
  </programme>
  <programme channel="400477" start="20260112030000 +0000" stop="20260112033000 +0000">
    <title lang="zh">TNT Sports Reload</title>
    <desc>The best bits from TNT Sports over the last week.</desc>
    <date>2026-01-12</date>
  </programme>
  <programme channel="400477" start="20260112033000 +0000" stop="20260112040000 +0000">
    <title lang="zh">Men's Alpine Skiing World Cup</title>
    <desc>Run one of the slalom from Adelboden, Switzerland.</desc>
    <date>2026-01-12</date>
  </programme>
  <programme channel="400477" start="20260112040000 +0000" stop="20260112043000 +0000">
    <title lang="zh">Men's Alpine Skiing World Cup</title>
    <desc>Run two of the slalom from Adelboden, Switzerland.</desc>
    <date>2026-01-12</date>
  </programme>
  <programme channel="400477" start="20260112043000 +0000" stop="20260112050000 +0000">
    <title lang="zh">Women's Alpine Skiing World Cup</title>
    <desc>Action from the super-G in Zauchensee, Austria.</desc>
    <date>2026-01-12</date>
  </programme>
  <programme channel="400477" start="20260112050000 +0000" stop="20260112053000 +0000">
    <title lang="zh">Ski Jumping World Cup</title>
    <desc>The women's team HS94 in Ljubno, Slovenia.</desc>
    <date>2026-01-12</date>
  </programme>
  <programme channel="400477" start="20260112053000 +0000" stop="20260112060000 +0000">
    <title lang="zh">Ski Jumping World Cup</title>
    <desc>The men's team HS140 in Zakopane, Poland.</desc>
    <date>2026-01-12</date>
  </programme>
  <programme channel="400477" start="20260112060000 +0000" stop="20260112070000 +0000">
    <title lang="zh">The Edge</title>
    <desc>"])&lt;/script&gt;&lt;script&gt;self.__next_f.push([1,"Highlights and analysis from the fifth Ashes Test.</desc>
    <date>2026-01-12</date>
  </programme>
  <programme channel="400477" start="20260112070000 +0000" stop="20260112080000 +0000">
    <title lang="zh">One Day International Cricket</title>
    <desc>Action from the first match between India and New Zealand.</desc>
    <date>2026-01-12</date>
  </programme>
  <programme channel="400477" start="20260112080000 +0000" stop="20260112090000 +0000">
    <title lang="zh">Serie A</title>
    <desc>AS Roma v Sassuolo.</desc>
    <date>2026-01-12</date>
  </programme>
  <programme channel="400477" start="20260112090000 +0000" stop="20260112100000 +0000">
    <title lang="zh">Serie A</title>
    <desc>Inter Milan v Napoli.</desc>
    <date>2026-01-12</date>
  </programme>
  <programme channel="400477" start="20260112100000 +0000" stop="20260112104500 +0000">
    <title lang="zh">Sign Up - Into Football</title>
    <desc>Wolves midfielder Joao Gomes talks to Damaris Cooke about his stutter and how he overcomes communication barriers. Plus, head coach Rob Edwards explains how he copes with pressure.</desc>
    <date>2026-01-12</date>
  </programme>
  <programme channel="400477" start="20260112104500 +0000" stop="20260112110000 +0000">
    <title lang="zh">Playing for Our Future - Cricket</title>
    <desc>Asking what the future holds for cricket in the battle against global warming. Reshmin Chowdhury meets people at all levels to discuss how cricket can be a force for change.</desc>
    <date>2026-01-12</date>
  </programme>
  <programme channel="400477" start="20260112110000 +0000" stop="20260112130000 +0000">
    <title lang="zh">Snooker Masters</title>
    <desc>Action from day one at Alexandra Palace.</desc>
    <date>2026-01-12</date>
  </programme>
  <programme channel="400477" start="20260112130000 +0000" stop="20260112163000 +0000">
    <title lang="zh">Live: Snooker Masters</title>
    <desc>Mark Williams v Mark Allen. Coverage of the third first-round match, held at Alexandra Palace in London. Williams is a two-time champion, prevailing back in 1998 and 2003, while Allen won the title in 2018.</desc>
    <date>2026-01-12</date>
  </programme>
  <programme channel="400477" start="20260112163000 +0000" stop="20260112173000 +0000">
    <title lang="zh">One Day International Cricket</title>
    <desc>Action from the first match between India and New Zealand.</desc>
    <date>2026-01-12</date>
  </programme>
  <programme channel="400477" start="20260112173000 +0000" stop="20260112183000 +0000">
    <title lang="zh">The Edge</title>
    <desc>"])&lt;/script&gt;&lt;script&gt;self.__next_f.push([1,"Highlights and analysis from the fifth Ashes Test.</desc>
    <date>2026-01-12</date>
  </programme>
  <programme channel="400477" start="20260112183000 +0000" stop="20260112221500 +0000">
    <title lang="zh">Live Emirates FA Cup</title>
    <desc>Liverpool v Barnsley (Kick-off 7.45pm). All the action from the third-round tie, held at Anfield. Barnsley have won on their last two visits to this ground, prevailing 1-0 in a Premier League fixture back in 1997, before claiming a shock 2-1 win in this competition in 2008, but Liverpool will be eager to avoid such a slip-up this evening having been eliminated from the Carabao Cup and dropped off </desc>
    <date>2026-01-12</date>
  </programme>
  <programme channel="400477" start="20260112221500 +0000" stop="20260112234500 +0000">
    <title lang="zh">FA Cup: The People's Story</title>
    <desc>Uncovering the untold stories of the FA Cup, revealing how it became a stage where sport and society collide, capturing the spirit of a nation through the beautiful game.</desc>
    <date>2026-01-12</date>
  </programme>
  <programme channel="400477" start="20260112234500 +0000" stop="20260113000000 +0000">
    <title lang="zh">Serie A</title>
    <desc>AS Roma v Sassuolo.</desc>
    <date>2026-01-12</date>
  </programme>
<channel id="400480">
    <display-name lang="United Kingdom of Great Britain and Northern Ireland">TNT Sports 2 HD</display-name>
    <icon src="" />
  </channel>
  <programme channel="400480" start="20260111000000 +0000" stop="20260111010000 +0000">
    <title lang="zh">The Edge</title>
    <desc>Highlights and analysis from the fifth Ashes Test).</desc>
    <date>2026-01-11</date>
  </programme>
  <programme channel="400480" start="20260111010000 +0000" stop="20260111013000 +0000">
    <title lang="zh">The Breakdown</title>
    <desc>Darren Fletcher is joined by Steven Gerrard, Ally McCoist, Steve McManaman and Joleon Lescott to discuss England and Scotland's chances at the 2026 FIFA World Cup.</desc>
    <date>2026-01-11</date>
  </programme>
  <programme channel="400480" start="20260111013000 +0000" stop="20260111020000 +0000">
    <title lang="zh">The Gruppetto</title>
    <desc>Rob Hatch presents news from the world of cycling.</desc>
    <date>2026-01-11</date>
  </programme>
  <programme channel="400480" start="20260111020000 +0000" stop="20260111030000 +0000">
    <title lang="zh">UFC</title>
    <desc>A review of the action in 2025.</desc>
    <date>2026-01-11</date>
  </programme>
  <programme channel="400480" start="20260111030000 +0000" stop="20260111040000 +0000">
    <title lang="zh">Hard Knocks: In Season with the NFC East</title>
    <desc>An inside look at the Dallas Cowboys, New York Giants, Washington Commanders, and Philadelphia Eagles during the final stretch of the NFL regular season and into the playoffs.</desc>
    <date>2026-01-11</date>
  </programme>
  <programme channel="400480" start="20260111040000 +0000" stop="20260111053000 +0000">
    <title lang="zh">Ultimate Pool</title>
    <desc>Action from Group One of the Women's Champions League.</desc>
    <date>2026-01-11</date>
  </programme>
  <programme channel="400480" start="20260111053000 +0000" stop="20260111060000 +0000">
    <title lang="zh">The Breakdown</title>
    <desc>Darren Fletcher is joined by Ally McCoist, Owen Hargreaves, Joe Cole and Joleon Lescott to discuss the dynamics of a football dressing room.</desc>
    <date>2026-01-11</date>
  </programme>
  <programme channel="400480" start="20260111060000 +0000" stop="20260111080000 +0000">
    <title lang="zh">Live: A-League Women</title>
    <desc>Melbourne Victory v Brisbane Roar (Kick-off 6.00am). Coverage of the match at Home of the Matildas.</desc>
    <date>2026-01-11</date>
  </programme>
  <programme channel="400480" start="20260111080000 +0000" stop="20260111090000 +0000">
    <title lang="zh">Live: IBSF World Cup</title>
    <desc>Coverage of the first heat of the Two Woman Bob in St Moritz-Celerina, Switzerland.</desc>
    <date>2026-01-11</date>
  </programme>
  <programme channel="400480" start="20260111090000 +0000" stop="20260111093000 +0000">
    <title lang="zh">The Breakdown</title>
    <desc>Darren Fletcher is joined by Ally McCoist, Owen Hargreaves, Joe Cole and Joleon Lescott to discuss the dynamics of a football dressing room.</desc>
    <date>2026-01-11</date>
  </programme>
  <programme channel="400480" start="20260111093000 +0000" stop="20260111103000 +0000">
    <title lang="zh">Live: IBSF World Cup</title>
    <desc>Coverage of the second heat of the Two Woman Bob in St Moritz-Celerina, Switzerland.</desc>
    <date>2026-01-11</date>
  </programme>
  <programme channel="400480" start="20260111103000 +0000" stop="20260111113000 +0000">
    <title lang="zh">Rylan: Homophobia, Football and Me</title>
    <desc>TV personality Rylan examines homosexuality within football. He takes a look at his own personal experiences and interviews numerous figures from the beautiful game.</desc>
    <date>2026-01-11</date>
  </programme>
  <programme channel="400480" start="20260111113000 +0000" stop="20260111143000 +0000">
    <title lang="zh">Live Emirates FA Cup</title>
    <desc>Derby County v Leeds United (kick-off 12.00pm). Coverage of the third-round tie at Pride Park. The sides last met in the Championship last term, when Leeds won 1-0 here and 2-0 at Elland Road en route to earning promotion to the Premier League.</desc>
    <date>2026-01-11</date>
  </programme>
  <programme channel="400480" start="20260111143000 +0000" stop="20260111150000 +0000">
    <title lang="zh">The Breakdown</title>
    <desc>Darren Fletcher is joined by Ally McCoist, Owen Hargreaves, Joe Cole and Joleon Lescott to discuss the dynamics of a football dressing room.</desc>
    <date>2026-01-11</date>
  </programme>
  <programme channel="400480" start="20260111150000 +0000" stop="20260111151500 +0000">
    <title lang="zh">The Breakdown</title>
    <desc>Darren Fletcher talks to former England midfielder Owen Hargreaves.</desc>
    <date>2026-01-11</date>
  </programme>
  <programme channel="400480" start="20260111151500 +0000" stop="20260111153000 +0000">
    <title lang="zh">The Breakdown</title>
    <desc>Joe Cole talks to new Chelsea manager Liam Rosenior.</desc>
    <date>2026-01-11</date>
  </programme>
  <programme channel="400480" start="20260111153000 +0000" stop="20260111190000 +0000">
    <title lang="zh">Live Emirates FA Cup</title>
    <desc>Manchester United v Brighton \u0026 Hove Albion (Kick-off 4.30pm). All the action from the third-round tie at Old Trafford. The sides have already met here in the Premier League this term, with United claiming a 4-2 win to avenge losses home and away to the Seagulls in the previous campaign. The hosts last won this competition in 2024 when they beat local rivals Manchester City 2-1 in the final.</desc>
    <date>2026-01-11</date>
  </programme>
  <programme channel="400480" start="20260111190000 +0000" stop="20260111193000 +0000">
    <title lang="zh">The Breakdown</title>
    <desc>Darren Fletcher is joined by Steven Gerrard, Ally McCoist, Steve McManaman and Joleon Lescott to discuss England and Scotland's chances at the 2026 FIFA World Cup.</desc>
    <date>2026-01-11</date>
  </programme>
  <programme channel="400480" start="20260111193000 +0000" stop="20260111214500 +0000">
    <title lang="zh">Live: Serie A</title>
    <desc>Inter Milan v Napoli (Kick-off 7.45pm). All the action from the Italian top-flight match at the San Siro.</desc>
    <date>2026-01-11</date>
  </programme>
  <programme channel="400480" start="20260111214500 +0000" stop="20260111220000 +0000">
    <title lang="zh">The Breakdown</title>
    <desc>Darren Fletcher talks to former England midfielder Owen Hargreaves.</desc>
    <date>2026-01-11</date>
  </programme>
  <programme channel="400480" start="20260111220000 +0000" stop="20260111230000 +0000">
    <title lang="zh">One Day International Cricket</title>
    <desc>Action from the first match between India and New Zealand.</desc>
    <date>2026-01-11</date>
  </programme>
  <programme channel="400480" start="20260111230000 +0000" stop="20260112000000 +0000">
    <title lang="zh">International T20 Cricket Highlights</title>
    <desc>Sri Lanka v Pakistan. Highlights of the third Twenty20 in the three-match series, which took place at Rangiri Dambulla International Stadium in Dambulla.</desc>
    <date>2026-01-11</date>
  </programme>
  <programme channel="400480" start="20260112000000 +0000" stop="20260112010000 +0000">
    <title lang="zh">The Edge</title>
    <desc>Highlights and analysis from the fifth Ashes Test).</desc>
    <date>2026-01-12</date>
  </programme>
  <programme channel="400480" start="20260112010000 +0000" stop="20260112020000 +0000">
    <title lang="zh">UFC: The Ultimate Fighter</title>
    <desc>Coached by Alexander Volkanovski and Brian Ortega, this documentary series follows MMA fighters as they train and compete against each other for a contract with the UFC.</desc>
    <date>2026-01-12</date>
  </programme>
  <programme channel="400480" start="20260112020000 +0000" stop="20260112030000 +0000">
    <title lang="zh">UFC: The Ultimate Fighter</title>
    <desc>Coached by Alexander Volkanovski and Brian Ortega, this documentary series follows MMA fighters as they train and compete against each other for a contract with the UFC.</desc>
    <date>2026-01-12</date>
  </programme>
  <programme channel="400480" start="20260112030000 +0000" stop="20260112040000 +0000">
    <title lang="zh">UFC: The Ultimate Fighter</title>
    <desc>Coached by Alexander Volkanovski and Brian Ortega, this documentary series follows MMA fighters as they train and compete against each other for a contract with the UFC.</desc>
    <date>2026-01-12</date>
  </programme>
  <programme channel="400480" start="20260112040000 +0000" stop="20260112050000 +0000">
    <title lang="zh">UFC: The Ultimate Fighter</title>
    <desc>Coached by Alexander Volkanovski and Brian Ortega, this documentary series follows MMA fighters as they train and compete against each other for a contract with the UFC.</desc>
    <date>2026-01-12</date>
  </programme>
  <programme channel="400480" start="20260112050000 +0000" stop="20260112053000 +0000">
    <title lang="zh">Formula E Unplugged</title>
    <desc>A look at two German teams - ABT and Porsche.</desc>
    <date>2026-01-12</date>
  </programme>
  <programme channel="400480" start="20260112053000 +0000" stop="20260112060000 +0000">
    <title lang="zh">Formula E Unplugged</title>
    <desc>Profiles of NEOM McLaren's Jake Hughes and Nissan's Sacha Fenestraz.</desc>
    <date>2026-01-12</date>
  </programme>
  <programme channel="400480" start="20260112060000 +0000" stop="20260112070000 +0000">
    <title lang="zh">Isuzu UTE A-League</title>
    <desc>Brisbane Roar v Auckland FC.</desc>
    <date>2026-01-12</date>
  </programme>
  <programme channel="400480" start="20260112070000 +0000" stop="20260112080000 +0000">
    <title lang="zh">Isuzu UTE A-League</title>
    <desc>Melbourne Victory v Western Sydney Wanderers.</desc>
    <date>2026-01-12</date>
  </programme>
  <programme channel="400480" start="20260112080000 +0000" stop="20260112090000 +0000">
    <title lang="zh">Isuzu UTE A-League</title>
    <desc>Macarthur FC v Sydney FC.</desc>
    <date>2026-01-12</date>
  </programme>
  <programme channel="400480" start="20260112090000 +0000" stop="20260112100000 +0000">
    <title lang="zh">Isuzu UTE A-League</title>
    <desc>Perth Glory v Central Coast Mariners.</desc>
    <date>2026-01-12</date>
  </programme>
  <programme channel="400480" start="20260112100000 +0000" stop="20260112110000 +0000">
    <title lang="zh">Isuzu UTE A-League</title>
    <desc>Wellington Phoenix v Adelaide United.</desc>
    <date>2026-01-12</date>
  </programme>
  <programme channel="400480" start="20260112110000 +0000" stop="20260112120000 +0000">
    <title lang="zh">Isuzu UTE A-League</title>
    <desc>Melbourne City v Newcastle Jets.</desc>
    <date>2026-01-12</date>
  </programme>
  <programme channel="400480" start="20260112120000 +0000" stop="20260112123000 +0000">
    <title lang="zh">Premier League Stories</title>
    <desc>A profile of Tottenham Hotspur defender Micky van de Ven.</desc>
    <date>2026-01-12</date>
  </programme>
  <programme channel="400480" start="20260112123000 +0000" stop="20260112130000 +0000">
    <title lang="zh">Premier League - The Big Interview</title>
    <desc>An in-depth interview with Georginio Rutter.</desc>
    <date>2026-01-12</date>
  </programme>
  <programme channel="400480" start="20260112130000 +0000" stop="20260112163000 +0000">
    <title lang="zh">Live: Snooker Masters</title>
    <desc>Mark Williams v Mark Allen. Coverage of the third first-round match, held at Alexandra Palace in London. Williams is a two-time champion, prevailing back in 1998 and 2003, while Allen won the title in 2018.</desc>
    <date>2026-01-12</date>
  </programme>
  <programme channel="400480" start="20260112163000 +0000" stop="20260112173000 +0000">
    <title lang="zh">ABB FIA Formula E World Championship Highlights</title>
    <desc>Action from the Mexico City E-Prix.</desc>
    <date>2026-01-12</date>
  </programme>
  <programme channel="400480" start="20260112173000 +0000" stop="20260112181500 +0000">
    <title lang="zh">Sign Up - Into Football</title>
    <desc>Wolves midfielder Joao Gomes talks to Damaris Cooke about his stutter and how he overcomes communication barriers. Plus, head coach Rob Edwards explains how he copes with pressure.</desc>
    <date>2026-01-12</date>
  </programme>
  <programme channel="400480" start="20260112181500 +0000" stop="20260112184500 +0000">
    <title lang="zh">Premier League Stories</title>
    <desc>A profile of Tottenham Hotspur defender Micky van de Ven.</desc>
    <date>2026-01-12</date>
  </programme>
  <programme channel="400480" start="20260112184500 +0000" stop="20260112190000 +0000">
    <title lang="zh">What I Wore</title>
    <desc>Real Madrid legend Michel Salgado describes his passion for football via the shirts which have defined his life.</desc>
    <date>2026-01-12</date>
  </programme>
  <programme channel="400480" start="20260112190000 +0000" stop="20260112223000 +0000">
    <title lang="zh">Live: Snooker Masters</title>
    <desc>Zhao Xintong v Gary Wilson. Coverage of the fourth first-round match, held at Alexandra Palace in London, played over the best of 11 frames. Zhao is the reigning world champion, but failed to progress beyond this stage in his only previous appearance in this tournament in 2022. Wilson is also yet to win a match in this competition, losing in the first round in both 2022 and last year.</desc>
    <date>2026-01-12</date>
  </programme>
  <programme channel="400480" start="20260112223000 +0000" stop="20260112230000 +0000">
    <title lang="zh">The Muddy Roots of Football - Part 1</title>
    <desc>Following a football team in the highlands of Ireland made of members of the same family who speak a language that none of their opponents understand.</desc>
    <date>2026-01-12</date>
  </programme>
  <programme channel="400480" start="20260112230000 +0000" stop="20260112233000 +0000">
    <title lang="zh">The Muddy Roots of Football - Part 2</title>
    <desc>A profile of an amateur Romanian football team forced to transplant a football pitch from a nearby village because of pollution created by industrial activity.</desc>
    <date>2026-01-12</date>
  </programme>
  <programme channel="400480" start="20260112233000 +0000" stop="20260113000000 +0000">
    <title lang="zh">The Muddy Roots of Football - Part 3</title>
    <desc>With a cemetery behind one of the goals, this is where players of Vilar de Barrio play. The clay pitch is described as the 'worst in Spain' and the coach is running for mayor.</desc>
    <date>2026-01-12</date>
  </programme>
  <programme channel="400480" start="20260113000000 +0000" stop="20260114000000 +0000">
    <title lang="zh">The Muddy Roots of Football - Part 4</title>
    <desc>In Ireland, a home captain recounts the previous night's Christmas party, and a tight and terrible game ends with the captain getting told off by his mother.</desc>
    <date>2026-01-13</date>
  </programme>
</tv>